kvh/kvh.py
kvh/salut.kvh
kvh/LICENSE
kvh/__init__.py
kvh/version.txt
kvh/ckvh.cpython-39-x86_64-linux-gnu.so
kvh.libs/libstdc++-496613c0.so.6.0.32
kvh.libs/libgcc_s-a3a07607.so.1
kvh-0.3.7.dist-info/RECORD
kvh-0.3.7.dist-info/METADATA
kvh-0.3.7.dist-info/WHEEL
